README.md
setup.py
ODBM_tools.egg-info/PKG-INFO
ODBM_tools.egg-info/SOURCES.txt
ODBM_tools.egg-info/dependency_links.txt
ODBM_tools.egg-info/requires.txt
ODBM_tools.egg-info/top_level.txt
odbm/events.py
odbm/mechanisms.py
odbm/modifiers.py
odbm/odbm.py
odbm/utils.py
odbm/vis.py